{
    "id": "W2800467206",
    "doi": "https://doi.org/10.1007/978-3-319-93701-4_42",
    "title": "an agent-based distributed approach for bike sharing systems",
    "display_name": "An Agent-Based Distributed Approach for Bike Sharing Systems",
    "publication_year": 2018,
    "publication_date": "2018-01-01",
    "ids": "{'openalex': 'https://openalex.org/W2800467206', 'doi': 'https://doi.org/10.1007/978-3-319-93701-4_42', 'mag': '2800467206'}",
    "language": "en",
    "primary_location": "{'is_oa': False, 'landing_page_url': 'https://doi.org/10.1007/978-3-319-93701-4_42', 'pdf_url': None, 'source': {'id': 'https://openalex.org/S106296714', 'display_name': 'Lecture notes in computer science', 'issn_l': '0302-9743', 'issn': ['0302-9743', '1611-3349'], 'is_oa': False, 'is_in_doaj': False, 'is_core': True, 'host_organization': 'https://openalex.org/P4310319900', 'host_organization_name': 'Springer Science+Business Media', 'host_organization_lineage': ['https://openalex.org/P4310319965', 'https://openalex.org/P4310319900'], 'host_organization_lineage_names': ['Springer Nature', 'Springer Science+Business Media'], 'type': 'book series'}, 'license': None, 'license_id': None, 'version': None, 'is_accepted': False, 'is_published': False}",
    "type": "book-chapter",
    "type_crossref": "book-chapter",
    "indexed_in": "['crossref']",
    "open_access": "{'is_oa': True, 'oa_status': 'green', 'oa_url': 'https://inria.hal.science/hal-01742091/document', 'any_repository_has_fulltext': True}",
    "authorships": "[{'author_position': 'first', 'author': {'id': 'https://openalex.org/A5022815943', 'display_name': 'Ningkui Wang', 'orcid': None}, 'institutions': [{'id': 'https://openalex.org/I4210115519', 'display_name': 'Centre de Recherche en Informatique', 'ror': 'https://ror.org/020cdve92', 'country_code': 'FR', 'type': 'facility', 'lineage': ['https://openalex.org/I190752583', 'https://openalex.org/I4210091621', 'https://openalex.org/I4210115519', 'https://openalex.org/I70768539']}, {'id': 'https://openalex.org/I2279609970', 'display_name': 'Universit\u00e9 de Lille', 'ror': 'https://ror.org/02kzqn938', 'country_code': 'FR', 'type': 'education', 'lineage': ['https://openalex.org/I2279609970']}], 'countries': ['FR'], 'is_corresponding': False, 'raw_author_name': 'Ningkui Wang', 'raw_affiliation_strings': ['CRIStAL - Centre de Recherche en Informatique, Signal et Automatique de Lille - UMR 9189 (Universit\u00e9 de Lille - Campus scientifique - B\u00e2timent ESPRIT - Avenue Henri Poincar\u00e9 - 59655 Villeneuve d\u2019Ascq - France)'], 'affiliations': [{'raw_affiliation_string': 'CRIStAL - Centre de Recherche en Informatique, Signal et Automatique de Lille - UMR 9189 (Universit\u00e9 de Lille - Campus scientifique - B\u00e2timent ESPRIT - Avenue Henri Poincar\u00e9 - 59655 Villeneuve d\u2019Ascq - France)', 'institution_ids': ['https://openalex.org/I4210115519', 'https://openalex.org/I2279609970']}]}, {'author_position': 'middle', 'author': {'id': 'https://openalex.org/A5075271121', 'display_name': 'Hayfa Zgaya', 'orcid': 'https://orcid.org/0000-0002-7761-7725'}, 'institutions': [{'id': 'https://openalex.org/I4210115519', 'display_name': 'Centre de Recherche en Informatique', 'ror': 'https://ror.org/020cdve92', 'country_code': 'FR', 'type': 'facility', 'lineage': ['https://openalex.org/I190752583', 'https://openalex.org/I4210091621', 'https://openalex.org/I4210115519', 'https://openalex.org/I70768539']}, {'id': 'https://openalex.org/I2279609970', 'display_name': 'Universit\u00e9 de Lille', 'ror': 'https://ror.org/02kzqn938', 'country_code': 'FR', 'type': 'education', 'lineage': ['https://openalex.org/I2279609970']}], 'countries': ['FR'], 'is_corresponding': False, 'raw_author_name': 'Hayfa Zgaya', 'raw_affiliation_strings': ['CRIStAL - Centre de Recherche en Informatique, Signal et Automatique de Lille - UMR 9189 (Universit\u00e9 de Lille - Campus scientifique - B\u00e2timent ESPRIT - Avenue Henri Poincar\u00e9 - 59655 Villeneuve d\u2019Ascq - France)', \"ILIS - Institut Lillois d'Ing\u00e9nierie de la Sant\u00e9 (42, rue Ambroise Par\u00e9 59120 - LOOS - France)\"], 'affiliations': [{'raw_affiliation_string': \"ILIS - Institut Lillois d'Ing\u00e9nierie de la Sant\u00e9 (42, rue Ambroise Par\u00e9 59120 - LOOS - France)\", 'institution_ids': []}, {'raw_affiliation_string': 'CRIStAL - Centre de Recherche en Informatique, Signal et Automatique de Lille - UMR 9189 (Universit\u00e9 de Lille - Campus scientifique - B\u00e2timent ESPRIT - Avenue Henri Poincar\u00e9 - 59655 Villeneuve d\u2019Ascq - France)', 'institution_ids': ['https://openalex.org/I4210115519', 'https://openalex.org/I2279609970']}]}, {'author_position': 'middle', 'author': {'id': 'https://openalex.org/A5045115675', 'display_name': 'Philippe Mathieu', 'orcid': 'https://orcid.org/0000-0003-2786-1209'}, 'institutions': [{'id': 'https://openalex.org/I4210115519', 'display_name': 'Centre de Recherche en Informatique', 'ror': 'https://ror.org/020cdve92', 'country_code': 'FR', 'type': 'facility', 'lineage': ['https://openalex.org/I190752583', 'https://openalex.org/I4210091621', 'https://openalex.org/I4210115519', 'https://openalex.org/I70768539']}, {'id': 'https://openalex.org/I2279609970', 'display_name': 'Universit\u00e9 de Lille', 'ror': 'https://ror.org/02kzqn938', 'country_code': 'FR', 'type': 'education', 'lineage': ['https://openalex.org/I2279609970']}], 'countries': ['FR'], 'is_corresponding': False, 'raw_author_name': 'Philippe Mathieu', 'raw_affiliation_strings': ['CRIStAL - Centre de Recherche en Informatique, Signal et Automatique de Lille - UMR 9189 (Universit\u00e9 de Lille - Campus scientifique - B\u00e2timent ESPRIT - Avenue Henri Poincar\u00e9 - 59655 Villeneuve d\u2019Ascq - France)', \"SMAC - Syst\u00e8mes Multi-Agents et Comportements (Cit\u00e9 scientifique, b\u00e2timent M3 59655 Villeneuve d'Ascq CEDEX - France)\", 'Universit\u00e9 de Lille (EPE Universit\u00e9 de Lille. -- 42 rue Paul Duez, 59000 Lille - France)'], 'affiliations': [{'raw_affiliation_string': \"SMAC - Syst\u00e8mes Multi-Agents et Comportements (Cit\u00e9 scientifique, b\u00e2timent M3 59655 Villeneuve d'Ascq CEDEX - France)\", 'institution_ids': []}, {'raw_affiliation_string': 'CRIStAL - Centre de Recherche en Informatique, Signal et Automatique de Lille - UMR 9189 (Universit\u00e9 de Lille - Campus scientifique - B\u00e2timent ESPRIT - Avenue Henri Poincar\u00e9 - 59655 Villeneuve d\u2019Ascq - France)', 'institution_ids': ['https://openalex.org/I4210115519', 'https://openalex.org/I2279609970']}, {'raw_affiliation_string': 'Universit\u00e9 de Lille (EPE Universit\u00e9 de Lille. -- 42 rue Paul Duez, 59000 Lille - France)', 'institution_ids': []}]}, {'author_position': 'last', 'author': {'id': 'https://openalex.org/A5019923976', 'display_name': 'Slim Hammadi', 'orcid': 'https://orcid.org/0000-0002-5187-4870'}, 'institutions': [{'id': 'https://openalex.org/I4210143894', 'display_name': \"Laboratoire d'Automatique, G\u00e9nie Informatique et Signal\", 'ror': 'https://ror.org/04wez4p43', 'country_code': 'FR', 'type': 'facility', 'lineage': ['https://openalex.org/I1294671590', 'https://openalex.org/I2279609970', 'https://openalex.org/I4210131494', 'https://openalex.org/I4210137101', 'https://openalex.org/I4210139971', 'https://openalex.org/I4210143894', 'https://openalex.org/I7454413']}, {'id': 'https://openalex.org/I4210115519', 'display_name': 'Centre de Recherche en Informatique', 'ror': 'https://ror.org/020cdve92', 'country_code': 'FR', 'type': 'facility', 'lineage': ['https://openalex.org/I190752583', 'https://openalex.org/I4210091621', 'https://openalex.org/I4210115519', 'https://openalex.org/I70768539']}, {'id': 'https://openalex.org/I2279609970', 'display_name': 'Universit\u00e9 de Lille', 'ror': 'https://ror.org/02kzqn938', 'country_code': 'FR', 'type': 'education', 'lineage': ['https://openalex.org/I2279609970']}], 'countries': ['FR'], 'is_corresponding': False, 'raw_author_name': 'Slim Hammadi', 'raw_affiliation_strings': ['CRIStAL - Centre de Recherche en Informatique, Signal et Automatique de Lille - UMR 9189 (Universit\u00e9 de Lille - Campus scientifique - B\u00e2timent ESPRIT - Avenue Henri Poincar\u00e9 - 59655 Villeneuve d\u2019Ascq - France)', 'LAGIS-OSL (France)'], 'affiliations': [{'raw_affiliation_string': 'LAGIS-OSL (France)', 'institution_ids': ['https://openalex.org/I4210143894']}, {'raw_affiliation_string': 'CRIStAL - Centre de Recherche en Informatique, Signal et Automatique de Lille - UMR 9189 (Universit\u00e9 de Lille - Campus scientifique - B\u00e2timent ESPRIT - Avenue Henri Poincar\u00e9 - 59655 Villeneuve d\u2019Ascq - France)', 'institution_ids': ['https://openalex.org/I4210115519', 'https://openalex.org/I2279609970']}]}]",
    "countries_distinct_count": 1,
    "institutions_distinct_count": 3,
    "corresponding_author_ids": "[]",
    "corresponding_institution_ids": "[]",
    "apc_list": "{'value': 5000, 'currency': 'EUR', 'value_usd': 5392, 'provenance': 'doaj'}",
    "apc_paid": NaN,
    "fwci": 0.71,
    "has_fulltext": true,
    "fulltext_origin": "pdf",
    "cited_by_count": 1,
    "cited_by_percentile_year": "{'min': 65, 'max': 72}",
    "biblio": "{'volume': None, 'issue': None, 'first_page': '540', 'last_page': '552'}",
    "is_retracted": false,
    "is_paratext": false,
    "primary_topic": "{'id': 'https://openalex.org/T11942', 'display_name': 'Implications of Shared Autonomous Vehicle Services', 'score': 0.9993, 'subfield': {'id': 'https://openalex.org/subfields/2203', 'display_name': 'Automotive Engineering'}, 'field': {'id': 'https://openalex.org/fields/22', 'display_name': 'Engineering'}, 'domain': {'id': 'https://openalex.org/domains/3', 'display_name': 'Physical Sciences'}}",
    "topics": "[{'id': 'https://openalex.org/T11942', 'display_name': 'Implications of Shared Autonomous Vehicle Services', 'score': 0.9993, 'subfield': {'id': 'https://openalex.org/subfields/2203', 'display_name': 'Automotive Engineering'}, 'field': {'id': 'https://openalex.org/fields/22', 'display_name': 'Engineering'}, 'domain': {'id': 'https://openalex.org/domains/3', 'display_name': 'Physical Sciences'}}, {'id': 'https://openalex.org/T11500', 'display_name': 'Modeling Pedestrian Dynamics and Evacuations', 'score': 0.9973, 'subfield': {'id': 'https://openalex.org/subfields/2212', 'display_name': 'Ocean Engineering'}, 'field': {'id': 'https://openalex.org/fields/22', 'display_name': 'Engineering'}, 'domain': {'id': 'https://openalex.org/domains/3', 'display_name': 'Physical Sciences'}}, {'id': 'https://openalex.org/T10698', 'display_name': 'Understanding Attitudes Towards Public Transport and Private Car', 'score': 0.9925, 'subfield': {'id': 'https://openalex.org/subfields/3313', 'display_name': 'Transportation'}, 'field': {'id': 'https://openalex.org/fields/33', 'display_name': 'Social Sciences'}, 'domain': {'id': 'https://openalex.org/domains/2', 'display_name': 'Social Sciences'}}]",
    "keywords": "[{'id': 'https://openalex.org/keywords/dynamic-ride-sharing', 'display_name': 'Dynamic Ride-Sharing', 'score': 0.581839}, {'id': 'https://openalex.org/keywords/agent-based-model', 'display_name': 'Agent-Based Model', 'score': 0.541729}, {'id': 'https://openalex.org/keywords/agent-based-modeling', 'display_name': 'Agent-Based Modeling', 'score': 0.541542}, {'id': 'https://openalex.org/keywords/carsharing-systems', 'display_name': 'Carsharing Systems', 'score': 0.512219}, {'id': 'https://openalex.org/keywords/ridesharing', 'display_name': 'Ridesharing', 'score': 0.504818}]",
    "concepts": "[{'id': 'https://openalex.org/C2994001137', 'wikidata': 'https://www.wikidata.org/wiki/Q1358919', 'display_name': 'Bike sharing', 'level': 2, 'score': 0.9206548}, {'id': 'https://openalex.org/C41008148', 'wikidata': 'https://www.wikidata.org/wiki/Q21198', 'display_name': 'Computer science', 'level': 0, 'score': 0.63560665}, {'id': 'https://openalex.org/C3017893058', 'wikidata': 'https://www.wikidata.org/wiki/Q999278', 'display_name': 'User satisfaction', 'level': 2, 'score': 0.4121775}, {'id': 'https://openalex.org/C107457646', 'wikidata': 'https://www.wikidata.org/wiki/Q207434', 'display_name': 'Human\u2013computer interaction', 'level': 1, 'score': 0.36399168}, {'id': 'https://openalex.org/C120314980', 'wikidata': 'https://www.wikidata.org/wiki/Q180634', 'display_name': 'Distributed computing', 'level': 1, 'score': 0.32329458}, {'id': 'https://openalex.org/C22212356', 'wikidata': 'https://www.wikidata.org/wiki/Q775325', 'display_name': 'Transport engineering', 'level': 1, 'score': 0.24432638}, {'id': 'https://openalex.org/C127413603', 'wikidata': 'https://www.wikidata.org/wiki/Q11023', 'display_name': 'Engineering', 'level': 0, 'score': 0.17446646}]",
    "mesh": "[]",
    "locations_count": 6,
    "locations": "[{'is_oa': False, 'landing_page_url': 'https://doi.org/10.1007/978-3-319-93701-4_42', 'pdf_url': None, 'source': {'id': 'https://openalex.org/S106296714', 'display_name': 'Lecture notes in computer science', 'issn_l': '0302-9743', 'issn': ['0302-9743', '1611-3349'], 'is_oa': False, 'is_in_doaj': False, 'is_core': True, 'host_organization': 'https://openalex.org/P4310319900', 'host_organization_name': 'Springer Science+Business Media', 'host_organization_lineage': ['https://openalex.org/P4310319965', 'https://openalex.org/P4310319900'], 'host_organization_lineage_names': ['Springer Nature', 'Springer Science+Business Media'], 'type': 'book series'}, 'license': None, 'license_id': None, 'version': None, 'is_accepted': False, 'is_published': False}, {'is_oa': False, 'landing_page_url': 'https://hal.inria.fr/hal-01742091', 'pdf_url': None, 'source': {'id': 'https://openalex.org/S4306402512', 'display_name': 'HAL (Le Centre pour la Communication Scientifique Directe)', 'issn_l': None, 'issn': None, 'is_oa': True, 'is_in_doaj': False, 'is_core': False, 'host_organization': 'https://openalex.org/I1294671590', 'host_organization_name': 'Centre National de la Recherche Scientifique', 'host_organization_lineage': ['https://openalex.org/I1294671590'], 'host_organization_lineage_names': ['Centre National de la Recherche Scientifique'], 'type': 'repository'}, 'license': None, 'license_id': None, 'version': None, 'is_accepted': False, 'is_published': False}, {'is_oa': True, 'landing_page_url': 'https://inria.hal.science/hal-01742091', 'pdf_url': 'https://inria.hal.science/hal-01742091/document', 'source': None, 'license': 'other-oa', 'license_id': 'https://openalex.org/licenses/other-oa', 'version': 'submittedVersion', 'is_accepted': False, 'is_published': False}, {'is_oa': True, 'landing_page_url': 'https://inria.hal.science/hal-01742091/file/Main.pdf', 'pdf_url': 'https://inria.hal.science/hal-01742091/file/Main.pdf', 'source': {'id': 'https://openalex.org/S4306402512', 'display_name': 'HAL (Le Centre pour la Communication Scientifique Directe)', 'issn_l': None, 'issn': None, 'is_oa': True, 'is_in_doaj': False, 'is_core': False, 'host_organization': 'https://openalex.org/I1294671590', 'host_organization_name': 'Centre National de la Recherche Scientifique', 'host_organization_lineage': ['https://openalex.org/I1294671590'], 'host_organization_lineage_names': ['Centre National de la Recherche Scientifique'], 'type': 'repository'}, 'license': None, 'license_id': None, 'version': 'submittedVersion', 'is_accepted': False, 'is_published': False}, {'is_oa': True, 'landing_page_url': 'http://hdl.handle.net/20.500.12210/23069', 'pdf_url': 'https://lilloa.univ-lille.fr/bitstream/20.500.12210/23069/1/https%3a//hal.inria.fr/hal-01742091/document', 'source': {'id': 'https://openalex.org/S4306402203', 'display_name': 'LillOA (Universit\u00e9 de Lille (University Of Lille))', 'issn_l': None, 'issn': None, 'is_oa': True, 'is_in_doaj': False, 'is_core': False, 'host_organization': 'https://openalex.org/I4210123514', 'host_organization_name': \"Centre d'Etudes en Civilisations, Langues et Litt\u00e9ratures Etrang\u00e8res\", 'host_organization_lineage': ['https://openalex.org/I4210123514'], 'host_organization_lineage_names': [\"Centre d'Etudes en Civilisations, Langues et Litt\u00e9ratures Etrang\u00e8res\"], 'type': 'repository'}, 'license': None, 'license_id': None, 'version': 'submittedVersion', 'is_accepted': False, 'is_published': False}, {'is_oa': True, 'landing_page_url': 'https://hal.inria.fr/hal-01742091/file/Main.pdf', 'pdf_url': 'https://hal.inria.fr/hal-01742091/file/Main.pdf', 'source': {'id': 'https://openalex.org/S4306402512', 'display_name': 'HAL (Le Centre pour la Communication Scientifique Directe)', 'issn_l': None, 'issn': None, 'is_oa': True, 'is_in_doaj': False, 'is_core': False, 'host_organization': 'https://openalex.org/I1294671590', 'host_organization_name': 'Centre National de la Recherche Scientifique', 'host_organization_lineage': ['https://openalex.org/I1294671590'], 'host_organization_lineage_names': ['Centre National de la Recherche Scientifique'], 'type': 'repository'}, 'license': None, 'license_id': None, 'version': 'submittedVersion', 'is_accepted': False, 'is_published': False}]",
    "best_oa_location": "{'is_oa': True, 'landing_page_url': 'https://inria.hal.science/hal-01742091', 'pdf_url': 'https://inria.hal.science/hal-01742091/document', 'source': None, 'license': 'other-oa', 'license_id': 'https://openalex.org/licenses/other-oa', 'version': 'submittedVersion', 'is_accepted': False, 'is_published': False}",
    "sustainable_development_goals": "[]",
    "grants": "[]",
    "datasets": "[]",
    "versions": "[]",
    "referenced_works_count": 23,
    "referenced_works": "['https://openalex.org/W1533164247', 'https://openalex.org/W1965945152', 'https://openalex.org/W1995279652', 'https://openalex.org/W2011776639', 'https://openalex.org/W2023689807', 'https://openalex.org/W2039205494', 'https://openalex.org/W2048382412', 'https://openalex.org/W2060463459', 'https://openalex.org/W2062147841', 'https://openalex.org/W2080113883', 'https://openalex.org/W2085203873', 'https://openalex.org/W2100843116', 'https://openalex.org/W2116554828', 'https://openalex.org/W2124344619', 'https://openalex.org/W2129633982', 'https://openalex.org/W2151828736', 'https://openalex.org/W2154163658', 'https://openalex.org/W2406470551', 'https://openalex.org/W2433151922', 'https://openalex.org/W2523951014', 'https://openalex.org/W2605114698', 'https://openalex.org/W2905316807', 'https://openalex.org/W4301347335']",
    "related_works": "['https://openalex.org/W2954294845', 'https://openalex.org/W2748952813', 'https://openalex.org/W2530322880', 'https://openalex.org/W2390279801', 'https://openalex.org/W2382290278', 'https://openalex.org/W2376932109', 'https://openalex.org/W2358668433', 'https://openalex.org/W2350741829', 'https://openalex.org/W2001405890', 'https://openalex.org/W1596801655']",
    "abstract_inverted_index": "{'Shared': [0], 'bikes': [1], 'are': [2, 35, 104], 'wildly': [3], 'welcomed': [4], 'and': [5, 38, 50, 82, 102, 110], 'becoming': [6], 'increasing': [7], 'popular': [8], 'in': [9], 'the': [10, 47, 93, 96, 108, 114, 121], 'world,': [11], 'as': [12], 'a': [13, 16, 77], 'result,': [14], 'quite': [15], 'few': [17], 'bike': [18, 28, 32, 43, 65, 80], 'sharing': [19, 33, 66], 'systems': [20, 34, 67], 'have': [21], 'been': [22], 'conducted': [23], 'to': [24, 91, 95, 106], 'provide': [25], 'services': [26], 'for': [27, 41, 64], 'users.': [29], 'However,': [30], 'current': [31], 'not': [36, 51], 'flexible': [37], 'considerate': [39], 'enough': [40], 'public': [42], 'users': [44, 75], 'because': [45], 'of': [46, 123], 'fixed': [48], 'stations': [49], 'well': [52], 'emphasized': [53], 'about': [54], \"user's\": [55, 89], 'satisfactions.': [56], 'In': [57], 'this': [58, 70], 'paper,': [59], 'an': [60], 'agent-based': [61], 'distributed': [62], 'approach': [63, 71], 'is': [68], 'proposed,': [69], 'aims': [72], 'at': [73], 'helping': [74], 'obtain': [76], 'needed': [78], 'shared': [79, 98], 'successfully': [81], 'efficiently.': [83], 'We': [84], 'pay': [85], 'more': [86], 'attention': [87], 'on': [88], 'preferences': [90], 'improve': [92, 107], 'satisfaction': [94], 'target': [97], 'bike,': [99], 'meanwhile,': [100], 'trust': [101], 'probability': [103], 'considered': [105], 'efficiency': [109], 'success': [111], 'rate.': [112], 'To': [113], 'end,': [115], 'results': [116], 'from': [117], 'simulation': [118], 'studies': [119], 'demonstrate': [120], 'effectiveness': [122], 'our': [124], 'proposed': [125], 'method.': [126]}",
    "cited_by_api_url": "https://api.openalex.org/works?filter=cites:W2800467206",
    "counts_by_year": "[{'year': 2019, 'cited_by_count': 1}]",
    "updated_date": "2024-07-25T18:30:23.013150",
    "created_date": "2018-05-17",
    "institution_assertions": NaN,
    "citation_normalized_percentile": NaN
}