{
    "meta": {
        "count": 5,
        "db_response_time_ms": 41,
        "page": 1,
        "per_page": 25,
        "groups_count": null
    },
    "results": [
        {
            "id": "https://openalex.org/W1984098334",
            "doi": "https://doi.org/10.1016/j.procs.2011.04.071",
            "title": "A natural language programming solution for executable papers",
            "display_name": "A natural language programming solution for executable papers",
            "publication_year": 2011,
            "publication_date": "2011-01-01",
            "ids": {
                "openalex": "https://openalex.org/W1984098334",
                "doi": "https://doi.org/10.1016/j.procs.2011.04.071",
                "mag": "1984098334"
            },
            "language": "en",
            "primary_location": {
                "is_oa": true,
                "landing_page_url": "https://doi.org/10.1016/j.procs.2011.04.071",
                "pdf_url": null,
                "source": {
                    "id": "https://openalex.org/S120348307",
                    "display_name": "Procedia Computer Science",
                    "issn_l": "1877-0509",
                    "issn": [
                        "1877-0509"
                    ],
                    "is_oa": true,
                    "is_in_doaj": false,
                    "is_core": true,
                    "host_organization": "https://openalex.org/P4310320990",
                    "host_organization_name": "Elsevier BV",
                    "host_organization_lineage": [
                        "https://openalex.org/P4310320990"
                    ],
                    "host_organization_lineage_names": [
                        "Elsevier BV"
                    ],
                    "type": "journal"
                },
                "license": null,
                "license_id": null,
                "version": "publishedVersion",
                "is_accepted": true,
                "is_published": true
            },
            "type": "article",
            "type_crossref": "journal-article",
            "indexed_in": [
                "crossref"
            ],
            "open_access": {
                "is_oa": true,
                "oa_status": "gold",
                "oa_url": "https://doi.org/10.1016/j.procs.2011.04.071",
                "any_repository_has_fulltext": false
            },
            "authorships": [
                {
                    "author_position": "first",
                    "author": {
                        "id": "https://openalex.org/A5058754653",
                        "display_name": "Sándor M. Veres",
                        "orcid": "https://orcid.org/0000-0003-0325-0710"
                    },
                    "institutions": [
                        {
                            "id": "https://openalex.org/I43439940",
                            "display_name": "University of Southampton",
                            "ror": "https://ror.org/01ryk1543",
                            "country_code": "GB",
                            "type": "education",
                            "lineage": [
                                "https://openalex.org/I43439940"
                            ]
                        }
                    ],
                    "countries": [
                        "GB"
                    ],
                    "is_corresponding": false,
                    "raw_author_name": "Sandor M Veres",
                    "raw_affiliation_strings": [
                        "Faculty of Engineering and the Environment University of Southampton, Highfield, Southamton, SO17 1BJ, UK"
                    ],
                    "affiliations": [
                        {
                            "raw_affiliation_string": "Faculty of Engineering and the Environment University of Southampton, Highfield, Southamton, SO17 1BJ, UK",
                            "institution_ids": [
                                "https://openalex.org/I43439940"
                            ]
                        }
                    ]
                },
                {
                    "author_position": "last",
                    "author": {
                        "id": "https://openalex.org/A5016768491",
                        "display_name": "Johan Adolfsson",
                        "orcid": null
                    },
                    "institutions": [
                        {
                            "id": "https://openalex.org/I43439940",
                            "display_name": "University of Southampton",
                            "ror": "https://ror.org/01ryk1543",
                            "country_code": "GB",
                            "type": "education",
                            "lineage": [
                                "https://openalex.org/I43439940"
                            ]
                        }
                    ],
                    "countries": [
                        "GB"
                    ],
                    "is_corresponding": false,
                    "raw_author_name": "J. Patrik Adolfsson",
                    "raw_affiliation_strings": [
                        "Faculty of Engineering and the Environment University of Southampton, Highfield, Southamton, SO17 1BJ, UK"
                    ],
                    "affiliations": [
                        {
                            "raw_affiliation_string": "Faculty of Engineering and the Environment University of Southampton, Highfield, Southamton, SO17 1BJ, UK",
                            "institution_ids": [
                                "https://openalex.org/I43439940"
                            ]
                        }
                    ]
                }
            ],
            "institution_assertions": [],
            "countries_distinct_count": 1,
            "institutions_distinct_count": 1,
            "corresponding_author_ids": [],
            "corresponding_institution_ids": [],
            "apc_list": null,
            "apc_paid": null,
            "fwci": 0.837,
            "has_fulltext": true,
            "fulltext_origin": "ngrams",
            "cited_by_count": 5,
            "citation_normalized_percentile": {
                "value": 0.811409,
                "is_in_top_1_percent": false,
                "is_in_top_10_percent": false
            },
            "cited_by_percentile_year": {
                "min": 80,
                "max": 81
            },
            "biblio": {
                "volume": "4",
                "issue": null,
                "first_page": "678",
                "last_page": "687"
            },
            "is_retracted": false,
            "is_paratext": false,
            "primary_topic": {
                "id": "https://openalex.org/T10906",
                "display_name": "Artificial Intelligence Planning and Reasoning",
                "score": 0.9975,
                "subfield": {
                    "id": "https://openalex.org/subfields/1702",
                    "display_name": "Artificial Intelligence"
                },
                "field": {
                    "id": "https://openalex.org/fields/17",
                    "display_name": "Computer Science"
                },
                "domain": {
                    "id": "https://openalex.org/domains/3",
                    "display_name": "Physical Sciences"
                }
            },
            "topics": [
                {
                    "id": "https://openalex.org/T10906",
                    "display_name": "Artificial Intelligence Planning and Reasoning",
                    "score": 0.9975,
                    "subfield": {
                        "id": "https://openalex.org/subfields/1702",
                        "display_name": "Artificial Intelligence"
                    },
                    "field": {
                        "id": "https://openalex.org/fields/17",
                        "display_name": "Computer Science"
                    },
                    "domain": {
                        "id": "https://openalex.org/domains/3",
                        "display_name": "Physical Sciences"
                    }
                },
                {
                    "id": "https://openalex.org/T10215",
                    "display_name": "Semantic Web and Ontology Development",
                    "score": 0.9906,
                    "subfield": {
                        "id": "https://openalex.org/subfields/1702",
                        "display_name": "Artificial Intelligence"
                    },
                    "field": {
                        "id": "https://openalex.org/fields/17",
                        "display_name": "Computer Science"
                    },
                    "domain": {
                        "id": "https://openalex.org/domains/3",
                        "display_name": "Physical Sciences"
                    }
                },
                {
                    "id": "https://openalex.org/T11986",
                    "display_name": "Management and Reproducibility of Scientific Workflows",
                    "score": 0.9882,
                    "subfield": {
                        "id": "https://openalex.org/subfields/1802",
                        "display_name": "Information Systems and Management"
                    },
                    "field": {
                        "id": "https://openalex.org/fields/18",
                        "display_name": "Decision Sciences"
                    },
                    "domain": {
                        "id": "https://openalex.org/domains/2",
                        "display_name": "Social Sciences"
                    }
                }
            ],
            "keywords": [
                {
                    "id": "https://openalex.org/keywords/executable",
                    "display_name": "Executable",
                    "score": 0.93669456
                },
                {
                    "id": "https://openalex.org/keywords/scientific-workflows",
                    "display_name": "Scientific Workflows",
                    "score": 0.520534
                }
            ],
            "concepts": [
                {
                    "id": "https://openalex.org/C160145156",
                    "wikidata": "https://www.wikidata.org/wiki/Q778586",
                    "display_name": "Executable",
                    "level": 2,
                    "score": 0.93669456
                },
                {
                    "id": "https://openalex.org/C41008148",
                    "wikidata": "https://www.wikidata.org/wiki/Q21198",
                    "display_name": "Computer science",
                    "level": 0,
                    "score": 0.9185751
                },
                {
                    "id": "https://openalex.org/C2778738651",
                    "wikidata": "https://www.wikidata.org/wiki/Q16546687",
                    "display_name": "Novelty",
                    "level": 2,
                    "score": 0.68309957
                },
                {
                    "id": "https://openalex.org/C206588197",
                    "wikidata": "https://www.wikidata.org/wiki/Q846574",
                    "display_name": "Reuse",
                    "level": 2,
                    "score": 0.56463075
                },
                {
                    "id": "https://openalex.org/C110875604",
                    "wikidata": "https://www.wikidata.org/wiki/Q75",
                    "display_name": "The Internet",
                    "level": 2,
                    "score": 0.5427021
                },
                {
                    "id": "https://openalex.org/C199360897",
                    "wikidata": "https://www.wikidata.org/wiki/Q9143",
                    "display_name": "Programming language",
                    "level": 1,
                    "score": 0.5135701
                },
                {
                    "id": "https://openalex.org/C136764020",
                    "wikidata": "https://www.wikidata.org/wiki/Q466",
                    "display_name": "World Wide Web",
                    "level": 1,
                    "score": 0.4154474
                },
                {
                    "id": "https://openalex.org/C115903868",
                    "wikidata": "https://www.wikidata.org/wiki/Q80993",
                    "display_name": "Software engineering",
                    "level": 1,
                    "score": 0.37752163
                },
                {
                    "id": "https://openalex.org/C18903297",
                    "wikidata": "https://www.wikidata.org/wiki/Q7150",
                    "display_name": "Ecology",
                    "level": 1,
                    "score": 0.0
                },
                {
                    "id": "https://openalex.org/C138885662",
                    "wikidata": "https://www.wikidata.org/wiki/Q5891",
                    "display_name": "Philosophy",
                    "level": 0,
                    "score": 0.0
                },
                {
                    "id": "https://openalex.org/C27206212",
                    "wikidata": "https://www.wikidata.org/wiki/Q34178",
                    "display_name": "Theology",
                    "level": 1,
                    "score": 0.0
                },
                {
                    "id": "https://openalex.org/C86803240",
                    "wikidata": "https://www.wikidata.org/wiki/Q420",
                    "display_name": "Biology",
                    "level": 0,
                    "score": 0.0
                }
            ],
            "mesh": [],
            "locations_count": 1,
            "locations": [
                {
                    "is_oa": true,
                    "landing_page_url": "https://doi.org/10.1016/j.procs.2011.04.071",
                    "pdf_url": null,
                    "source": {
                        "id": "https://openalex.org/S120348307",
                        "display_name": "Procedia Computer Science",
                        "issn_l": "1877-0509",
                        "issn": [
                            "1877-0509"
                        ],
                        "is_oa": true,
                        "is_in_doaj": false,
                        "is_core": true,
                        "host_organization": "https://openalex.org/P4310320990",
                        "host_organization_name": "Elsevier BV",
                        "host_organization_lineage": [
                            "https://openalex.org/P4310320990"
                        ],
                        "host_organization_lineage_names": [
                            "Elsevier BV"
                        ],
                        "type": "journal"
                    },
                    "license": null,
                    "license_id": null,
                    "version": "publishedVersion",
                    "is_accepted": true,
                    "is_published": true
                }
            ],
            "best_oa_location": {
                "is_oa": true,
                "landing_page_url": "https://doi.org/10.1016/j.procs.2011.04.071",
                "pdf_url": null,
                "source": {
                    "id": "https://openalex.org/S120348307",
                    "display_name": "Procedia Computer Science",
                    "issn_l": "1877-0509",
                    "issn": [
                        "1877-0509"
                    ],
                    "is_oa": true,
                    "is_in_doaj": false,
                    "is_core": true,
                    "host_organization": "https://openalex.org/P4310320990",
                    "host_organization_name": "Elsevier BV",
                    "host_organization_lineage": [
                        "https://openalex.org/P4310320990"
                    ],
                    "host_organization_lineage_names": [
                        "Elsevier BV"
                    ],
                    "type": "journal"
                },
                "license": null,
                "license_id": null,
                "version": "publishedVersion",
                "is_accepted": true,
                "is_published": true
            },
            "sustainable_development_goals": [
                {
                    "score": 0.85,
                    "display_name": "Quality education",
                    "id": "https://metadata.un.org/sdg/4"
                }
            ],
            "grants": [],
            "datasets": [],
            "versions": [],
            "referenced_works_count": 3,
            "referenced_works": [
                "https://openalex.org/W12141027",
                "https://openalex.org/W1535440640",
                "https://openalex.org/W1997929601"
            ],
            "related_works": [
                "https://openalex.org/W82161441",
                "https://openalex.org/W4288804799",
                "https://openalex.org/W3126131230",
                "https://openalex.org/W2751208925",
                "https://openalex.org/W2381242807",
                "https://openalex.org/W2347541121",
                "https://openalex.org/W2181943964",
                "https://openalex.org/W1990602094",
                "https://openalex.org/W1576042299",
                "https://openalex.org/W1528423264"
            ],
            "abstract_inverted_index": {
                "The": [
                    0,
                    24
                ],
                "paper": [
                    1,
                    30
                ],
                "describes": [
                    2
                ],
                "a": [
                    3,
                    29,
                    72
                ],
                "system": [
                    4,
                    69
                ],
                "for": [
                    5,
                    8
                ],
                "executable": [
                    6,
                    25,
                    62
                ],
                "papers": [
                    7,
                    100
                ],
                "publishers": [
                    9
                ],
                "enabling": [
                    10
                ],
                "them": [
                    11
                ],
                "to": [
                    12,
                    16,
                    49,
                    59,
                    93
                ],
                "reuse": [
                    13
                ],
                "content": [
                    14
                ],
                "and": [
                    15,
                    22,
                    37,
                    96
                ],
                "generate": [
                    17
                ],
                "further": [
                    18
                ],
                "advances": [
                    19
                ],
                "of": [
                    20,
                    74,
                    81,
                    98
                ],
                "science": [
                    21
                ],
                "engineering.": [
                    23
                ],
                "algorithmic": [
                    26,
                    75
                ],
                "descriptions": [
                    27
                ],
                "within": [
                    28
                ],
                "are": [
                    31,
                    47
                ],
                "presented": [
                    32
                ],
                "in": [
                    33,
                    84
                ],
                "natural": [
                    34
                ],
                "language": [
                    35
                ],
                "sentences": [
                    36
                ],
                "basic": [
                    38
                ],
                "code,": [
                    39
                ],
                "thereby": [
                    40
                ],
                "making": [
                    41
                ],
                "long": [
                    42
                ],
                "term": [
                    43
                ],
                "compatibility": [
                    44
                ],
                "absolute.": [
                    45
                ],
                "Authors": [
                    46
                ],
                "required": [
                    48
                ],
                "use": [
                    50
                ],
                "publicly": [
                    51
                ],
                "numerical": [
                    52
                ],
                "libraries": [
                    53
                ],
                "on": [
                    54,
                    77
                ],
                "the": [
                    55,
                    68,
                    78
                ],
                "Internet": [
                    56
                ],
                "or": [
                    57
                ],
                "references": [
                    58
                ],
                "publications": [
                    60,
                    85
                ],
                "with": [
                    61
                ],
                "papers.": [
                    63
                ],
                "As": [
                    64
                ],
                "used": [
                    65
                ],
                "by": [
                    66,
                    89
                ],
                "authors": [
                    67
                ],
                "automatically": [
                    70
                ],
                "creates": [
                    71
                ],
                "web": [
                    73
                ],
                "knowledge": [
                    76
                ],
                "Internet.": [
                    79
                ],
                "Novelty": [
                    80
                ],
                "new": [
                    82
                ],
                "algorithms": [
                    83
                ],
                "can": [
                    86
                ],
                "be": [
                    87
                ],
                "evaluated": [
                    88
                ],
                "automated": [
                    90
                ],
                "tools": [
                    91
                ],
                "available": [
                    92
                ],
                "authors,": [
                    94
                ],
                "reviewers": [
                    95
                ],
                "readers": [
                    97
                ],
                "scientific": [
                    99
                ],
                "published.": [
                    101
                ]
            },
            "cited_by_api_url": "https://api.openalex.org/works?filter=cites:W1984098334",
            "counts_by_year": [
                {
                    "year": 2024,
                    "cited_by_count": 1
                },
                {
                    "year": 2017,
                    "cited_by_count": 2
                },
                {
                    "year": 2012,
                    "cited_by_count": 1
                }
            ],
            "updated_date": "2024-09-24T00:53:09.567303",
            "created_date": "2016-06-24"
        },
        {
            "id": "https://openalex.org/W40040301",
            "doi": null,
            "title": "Patientens upplevelse av att bli vårdad av deltidsbrandmän i samband med akut bröstsmärta: En kvalitativ intervjustudie om att bli akut sjuk på landsbygden",
            "display_name": "Patientens upplevelse av att bli vårdad av deltidsbrandmän i samband med akut bröstsmärta: En kvalitativ intervjustudie om att bli akut sjuk på landsbygden",
            "publication_year": 2014,
            "publication_date": "2014-07-31",
            "ids": {
                "openalex": "https://openalex.org/W40040301",
                "mag": "40040301"
            },
            "language": "sv",
            "primary_location": {
                "is_oa": false,
                "landing_page_url": "http://www.diva-portal.org/smash/record.jsf?pid=diva2:1309855",
                "pdf_url": null,
                "source": null,
                "license": null,
                "license_id": null,
                "version": null,
                "is_accepted": false,
                "is_published": false
            },
            "type": "article",
            "type_crossref": "journal-article",
            "indexed_in": [],
            "open_access": {
                "is_oa": false,
                "oa_status": "closed",
                "oa_url": null,
                "any_repository_has_fulltext": false
            },
            "authorships": [
                {
                    "author_position": "first",
                    "author": {
                        "id": "https://openalex.org/A5016768491",
                        "display_name": "Johan Adolfsson",
                        "orcid": null
                    },
                    "institutions": [],
                    "countries": [],
                    "is_corresponding": false,
                    "raw_author_name": "Johan Adolfsson",
                    "raw_affiliation_strings": [],
                    "affiliations": []
                },
                {
                    "author_position": "last",
                    "author": {
                        "id": "https://openalex.org/A5085433612",
                        "display_name": "Mikael Jardenius",
                        "orcid": null
                    },
                    "institutions": [],
                    "countries": [],
                    "is_corresponding": false,
                    "raw_author_name": "Mikael Jardenius",
                    "raw_affiliation_strings": [],
                    "affiliations": []
                }
            ],
            "institution_assertions": [],
            "countries_distinct_count": 0,
            "institutions_distinct_count": 0,
            "corresponding_author_ids": [],
            "corresponding_institution_ids": [],
            "apc_list": null,
            "apc_paid": null,
            "fwci": 0.0,
            "has_fulltext": false,
            "cited_by_count": 0,
            "citation_normalized_percentile": {
                "value": 0.0,
                "is_in_top_1_percent": false,
                "is_in_top_10_percent": false
            },
            "cited_by_percentile_year": {
                "min": 0,
                "max": 66
            },
            "biblio": {
                "volume": null,
                "issue": null,
                "first_page": null,
                "last_page": null
            },
            "is_retracted": false,
            "is_paratext": false,
            "primary_topic": {
                "id": "https://openalex.org/T12947",
                "display_name": "Salutogenesis and Sense of Coherence in Health",
                "score": 0.9875,
                "subfield": {
                    "id": "https://openalex.org/subfields/3600",
                    "display_name": "General Health Professions"
                },
                "field": {
                    "id": "https://openalex.org/fields/36",
                    "display_name": "Health Professions"
                },
                "domain": {
                    "id": "https://openalex.org/domains/4",
                    "display_name": "Health Sciences"
                }
            },
            "topics": [
                {
                    "id": "https://openalex.org/T12947",
                    "display_name": "Salutogenesis and Sense of Coherence in Health",
                    "score": 0.9875,
                    "subfield": {
                        "id": "https://openalex.org/subfields/3600",
                        "display_name": "General Health Professions"
                    },
                    "field": {
                        "id": "https://openalex.org/fields/36",
                        "display_name": "Health Professions"
                    },
                    "domain": {
                        "id": "https://openalex.org/domains/4",
                        "display_name": "Health Sciences"
                    }
                },
                {
                    "id": "https://openalex.org/T11141",
                    "display_name": "Pediatric Cancer and Quality of Life",
                    "score": 0.9332,
                    "subfield": {
                        "id": "https://openalex.org/subfields/2735",
                        "display_name": "Pediatrics, Perinatology and Child Health"
                    },
                    "field": {
                        "id": "https://openalex.org/fields/27",
                        "display_name": "Medicine"
                    },
                    "domain": {
                        "id": "https://openalex.org/domains/4",
                        "display_name": "Health Sciences"
                    }
                },
                {
                    "id": "https://openalex.org/T11095",
                    "display_name": "Emergency Department Crowding",
                    "score": 0.9188,
                    "subfield": {
                        "id": "https://openalex.org/subfields/2711",
                        "display_name": "Emergency Medicine"
                    },
                    "field": {
                        "id": "https://openalex.org/fields/27",
                        "display_name": "Medicine"
                    },
                    "domain": {
                        "id": "https://openalex.org/domains/4",
                        "display_name": "Health Sciences"
                    }
                }
            ],
            "keywords": [
                {
                    "id": "https://openalex.org/keywords/ambulance-diversion",
                    "display_name": "Ambulance Diversion",
                    "score": 0.502063
                }
            ],
            "concepts": [
                {
                    "id": "https://openalex.org/C71924100",
                    "wikidata": "https://www.wikidata.org/wiki/Q11190",
                    "display_name": "Medicine",
                    "level": 0,
                    "score": 0.58439416
                }
            ],
            "mesh": [],
            "locations_count": 1,
            "locations": [
                {
                    "is_oa": false,
                    "landing_page_url": "http://www.diva-portal.org/smash/record.jsf?pid=diva2:1309855",
                    "pdf_url": null,
                    "source": null,
                    "license": null,
                    "license_id": null,
                    "version": null,
                    "is_accepted": false,
                    "is_published": false
                }
            ],
            "best_oa_location": null,
            "sustainable_development_goals": [],
            "grants": [],
            "datasets": [],
            "versions": [],
            "referenced_works_count": 24,
            "referenced_works": [
                "https://openalex.org/W1508775771",
                "https://openalex.org/W1564961393",
                "https://openalex.org/W1572092804",
                "https://openalex.org/W172647904",
                "https://openalex.org/W1976971266",
                "https://openalex.org/W1985952174",
                "https://openalex.org/W1998748345",
                "https://openalex.org/W2003550496",
                "https://openalex.org/W2043470904",
                "https://openalex.org/W2047739869",
                "https://openalex.org/W2051318600",
                "https://openalex.org/W2057867580",
                "https://openalex.org/W2064801425",
                "https://openalex.org/W2073608425",
                "https://openalex.org/W2083086696",
                "https://openalex.org/W2112743461",
                "https://openalex.org/W2121619422",
                "https://openalex.org/W2122240617",
                "https://openalex.org/W2142225512",
                "https://openalex.org/W2156086828",
                "https://openalex.org/W2159168909",
                "https://openalex.org/W2162272125",
                "https://openalex.org/W299695969",
                "https://openalex.org/W3146683351"
            ],
            "related_works": [],
            "abstract_inverted_index": {
                "Raddningstjansten": [
                    0,
                    18
                ],
                "ar": [
                    1,
                    14
                ],
                "i": [
                    2
                ],
                "stor": [
                    3
                ],
                "utstrackning": [
                    4
                ],
                "utplacerad": [
                    5
                ],
                "pa": [
                    6
                ],
                "sma": [
                    7
                ],
                "orter": [
                    8
                ],
                "och": [
                    9
                ],
                "har": [
                    10,
                    19
                ],
                "betydligt": [
                    11
                ],
                "fler": [
                    12
                ],
                "stationer": [
                    13
                ],
                "vad": [
                    15
                ],
                "ambulanssjukvarden": [
                    16,
                    23
                ],
                "har.": [
                    17
                ],
                "storre": [
                    20
                ],
                "mojligheter": [
                    21
                ],
                "an": [
                    22
                ],
                "att": [
                    24
                ],
                "s": [
                    25
                ],
                "...": [
                    26
                ]
            },
            "cited_by_api_url": "https://api.openalex.org/works?filter=cites:W40040301",
            "counts_by_year": [],
            "updated_date": "2024-09-19T14:31:10.930697",
            "created_date": "2016-06-24"
        },
        {
            "id": "https://openalex.org/W1517200793",
            "doi": null,
            "title": "Utveckling av barnvagn",
            "display_name": "Utveckling av barnvagn",
            "publication_year": 2008,
            "publication_date": "2008-01-01",
            "ids": {
                "openalex": "https://openalex.org/W1517200793",
                "mag": "1517200793"
            },
            "language": "en",
            "primary_location": {
                "is_oa": false,
                "landing_page_url": "http://kth.diva-portal.org/smash/get/diva2:543109/FULLTEXT01",
                "pdf_url": null,
                "source": null,
                "license": null,
                "license_id": null,
                "version": null,
                "is_accepted": false,
                "is_published": false
            },
            "type": "article",
            "type_crossref": "journal-article",
            "indexed_in": [],
            "open_access": {
                "is_oa": false,
                "oa_status": "closed",
                "oa_url": null,
                "any_repository_has_fulltext": false
            },
            "authorships": [
                {
                    "author_position": "first",
                    "author": {
                        "id": "https://openalex.org/A5016768491",
                        "display_name": "Johan Adolfsson",
                        "orcid": null
                    },
                    "institutions": [],
                    "countries": [],
                    "is_corresponding": false,
                    "raw_author_name": "Johan Adolfsson",
                    "raw_affiliation_strings": [],
                    "affiliations": []
                },
                {
                    "author_position": "last",
                    "author": {
                        "id": "https://openalex.org/A5002510709",
                        "display_name": "David Thalén",
                        "orcid": null
                    },
                    "institutions": [],
                    "countries": [],
                    "is_corresponding": false,
                    "raw_author_name": "David Thalén",
                    "raw_affiliation_strings": [],
                    "affiliations": []
                }
            ],
            "institution_assertions": [],
            "countries_distinct_count": 0,
            "institutions_distinct_count": 0,
            "corresponding_author_ids": [],
            "corresponding_institution_ids": [],
            "apc_list": null,
            "apc_paid": null,
            "fwci": 0.0,
            "has_fulltext": false,
            "cited_by_count": 0,
            "citation_normalized_percentile": {
                "value": 0.0,
                "is_in_top_1_percent": false,
                "is_in_top_10_percent": false
            },
            "cited_by_percentile_year": {
                "min": 0,
                "max": 63
            },
            "biblio": {
                "volume": null,
                "issue": null,
                "first_page": null,
                "last_page": null
            },
            "is_retracted": false,
            "is_paratext": false,
            "primary_topic": {
                "id": "https://openalex.org/T12021",
                "display_name": "Research Methodology in Social Sciences and Education",
                "score": 0.6491,
                "subfield": {
                    "id": "https://openalex.org/subfields/3304",
                    "display_name": "Education"
                },
                "field": {
                    "id": "https://openalex.org/fields/33",
                    "display_name": "Social Sciences"
                },
                "domain": {
                    "id": "https://openalex.org/domains/2",
                    "display_name": "Social Sciences"
                }
            },
            "topics": [
                {
                    "id": "https://openalex.org/T12021",
                    "display_name": "Research Methodology in Social Sciences and Education",
                    "score": 0.6491,
                    "subfield": {
                        "id": "https://openalex.org/subfields/3304",
                        "display_name": "Education"
                    },
                    "field": {
                        "id": "https://openalex.org/fields/33",
                        "display_name": "Social Sciences"
                    },
                    "domain": {
                        "id": "https://openalex.org/domains/2",
                        "display_name": "Social Sciences"
                    }
                }
            ],
            "keywords": [
                {
                    "id": "https://openalex.org/keywords/elite",
                    "display_name": "Elite",
                    "score": 0.41693646
                },
                {
                    "id": "https://openalex.org/keywords/learning",
                    "display_name": "Learning",
                    "score": 0.403656
                }
            ],
            "concepts": [
                {
                    "id": "https://openalex.org/C144133560",
                    "wikidata": "https://www.wikidata.org/wiki/Q4830453",
                    "display_name": "Business",
                    "level": 0,
                    "score": 0.45155537
                },
                {
                    "id": "https://openalex.org/C2775987171",
                    "wikidata": "https://www.wikidata.org/wiki/Q192797",
                    "display_name": "Elite",
                    "level": 3,
                    "score": 0.41693646
                },
                {
                    "id": "https://openalex.org/C112698675",
                    "wikidata": "https://www.wikidata.org/wiki/Q37038",
                    "display_name": "Advertising",
                    "level": 1,
                    "score": 0.34117982
                },
                {
                    "id": "https://openalex.org/C17744445",
                    "wikidata": "https://www.wikidata.org/wiki/Q36442",
                    "display_name": "Political science",
                    "level": 0,
                    "score": 0.17487174
                },
                {
                    "id": "https://openalex.org/C199539241",
                    "wikidata": "https://www.wikidata.org/wiki/Q7748",
                    "display_name": "Law",
                    "level": 1,
                    "score": 0.0
                },
                {
                    "id": "https://openalex.org/C94625758",
                    "wikidata": "https://www.wikidata.org/wiki/Q7163",
                    "display_name": "Politics",
                    "level": 2,
                    "score": 0.0
                }
            ],
            "mesh": [],
            "locations_count": 1,
            "locations": [
                {
                    "is_oa": false,
                    "landing_page_url": "http://kth.diva-portal.org/smash/get/diva2:543109/FULLTEXT01",
                    "pdf_url": null,
                    "source": null,
                    "license": null,
                    "license_id": null,
                    "version": null,
                    "is_accepted": false,
                    "is_published": false
                }
            ],
            "best_oa_location": null,
            "sustainable_development_goals": [
                {
                    "score": 0.43,
                    "display_name": "Industry, innovation and infrastructure",
                    "id": "https://metadata.un.org/sdg/9"
                }
            ],
            "grants": [],
            "datasets": [],
            "versions": [],
            "referenced_works_count": 0,
            "referenced_works": [],
            "related_works": [],
            "abstract_inverted_index": {
                "After": [
                    0
                ],
                "contacting": [
                    1
                ],
                "the": [
                    2,
                    12,
                    20
                ],
                "company": [
                    3
                ],
                "Elite": [
                    4
                ],
                "Group": [
                    5
                ],
                "Sverige": [
                    6
                ],
                "AB,": [
                    7
                ],
                "who": [
                    8
                ],
                "sells": [
                    9
                ],
                "strollers": [
                    10
                ],
                "under": [
                    11
                ],
                "brand": [
                    13
                ],
                "Crescent": [
                    14
                ],
                "Baby,": [
                    15
                ],
                "it": [
                    16
                ],
                "was": [
                    17,
                    31
                ],
                "determined": [
                    18
                ],
                "that": [
                    19
                ],
                "project": [
                    21
                ],
                "group": [
                    22
                ],
                "were": [
                    23
                ],
                "to": [
                    24
                ],
                "develop": [
                    25
                ],
                "a": [
                    26
                ],
                "three": [
                    27
                ],
                "wheeled": [
                    28
                ],
                "stroller": [
                    29
                ],
                "which": [
                    30
                ],
                "g": [
                    32
                ],
                "...": [
                    33
                ]
            },
            "cited_by_api_url": "https://api.openalex.org/works?filter=cites:W1517200793",
            "counts_by_year": [],
            "updated_date": "2024-09-19T06:35:01.953477",
            "created_date": "2016-06-24"
        },
        {
            "id": "https://openalex.org/W54315794",
            "doi": null,
            "title": "Venture Capitalists on the Seed Stage Arena : A Fit or Misfit",
            "display_name": "Venture Capitalists on the Seed Stage Arena : A Fit or Misfit",
            "publication_year": 2003,
            "publication_date": "2003-01-01",
            "ids": {
                "openalex": "https://openalex.org/W54315794",
                "mag": "54315794"
            },
            "language": "en",
            "primary_location": {
                "is_oa": false,
                "landing_page_url": "http://liu.diva-portal.org/smash/record.jsf?pid=diva2:19204",
                "pdf_url": null,
                "source": null,
                "license": null,
                "license_id": null,
                "version": null,
                "is_accepted": false,
                "is_published": false
            },
            "type": "article",
            "type_crossref": "journal-article",
            "indexed_in": [],
            "open_access": {
                "is_oa": false,
                "oa_status": "closed",
                "oa_url": null,
                "any_repository_has_fulltext": false
            },
            "authorships": [
                {
                    "author_position": "first",
                    "author": {
                        "id": "https://openalex.org/A5016768491",
                        "display_name": "Johan Adolfsson",
                        "orcid": null
                    },
                    "institutions": [],
                    "countries": [],
                    "is_corresponding": true,
                    "raw_author_name": "Johan Adolfsson",
                    "raw_affiliation_strings": [],
                    "affiliations": []
                }
            ],
            "institution_assertions": [],
            "countries_distinct_count": 0,
            "institutions_distinct_count": 0,
            "corresponding_author_ids": [
                "https://openalex.org/A5016768491"
            ],
            "corresponding_institution_ids": [],
            "apc_list": null,
            "apc_paid": null,
            "fwci": 0.0,
            "has_fulltext": false,
            "cited_by_count": 0,
            "citation_normalized_percentile": {
                "value": 0.0,
                "is_in_top_1_percent": false,
                "is_in_top_10_percent": false
            },
            "cited_by_percentile_year": {
                "min": 0,
                "max": 59
            },
            "biblio": {
                "volume": null,
                "issue": null,
                "first_page": null,
                "last_page": null
            },
            "is_retracted": false,
            "is_paratext": false,
            "primary_topic": {
                "id": "https://openalex.org/T11903",
                "display_name": "Venture Capital and Start-Up Financing",
                "score": 0.9999,
                "subfield": {
                    "id": "https://openalex.org/subfields/1402",
                    "display_name": "Accounting"
                },
                "field": {
                    "id": "https://openalex.org/fields/14",
                    "display_name": "Business, Management and Accounting"
                },
                "domain": {
                    "id": "https://openalex.org/domains/2",
                    "display_name": "Social Sciences"
                }
            },
            "topics": [
                {
                    "id": "https://openalex.org/T11903",
                    "display_name": "Venture Capital and Start-Up Financing",
                    "score": 0.9999,
                    "subfield": {
                        "id": "https://openalex.org/subfields/1402",
                        "display_name": "Accounting"
                    },
                    "field": {
                        "id": "https://openalex.org/fields/14",
                        "display_name": "Business, Management and Accounting"
                    },
                    "domain": {
                        "id": "https://openalex.org/domains/2",
                        "display_name": "Social Sciences"
                    }
                },
                {
                    "id": "https://openalex.org/T10058",
                    "display_name": "Entrepreneurship and Business Innovation",
                    "score": 0.9839,
                    "subfield": {
                        "id": "https://openalex.org/subfields/1405",
                        "display_name": "Management of Technology and Innovation"
                    },
                    "field": {
                        "id": "https://openalex.org/fields/14",
                        "display_name": "Business, Management and Accounting"
                    },
                    "domain": {
                        "id": "https://openalex.org/domains/2",
                        "display_name": "Social Sciences"
                    }
                },
                {
                    "id": "https://openalex.org/T12722",
                    "display_name": "The Impact of R&D Subsidies on Private R&D Investment",
                    "score": 0.9477,
                    "subfield": {
                        "id": "https://openalex.org/subfields/2002",
                        "display_name": "Economics and Econometrics"
                    },
                    "field": {
                        "id": "https://openalex.org/fields/20",
                        "display_name": "Economics, Econometrics and Finance"
                    },
                    "domain": {
                        "id": "https://openalex.org/domains/2",
                        "display_name": "Social Sciences"
                    }
                }
            ],
            "keywords": [
                {
                    "id": "https://openalex.org/keywords/venture-growth",
                    "display_name": "Venture Growth",
                    "score": 0.55984
                },
                {
                    "id": "https://openalex.org/keywords/entrepreneurship",
                    "display_name": "Entrepreneurship",
                    "score": 0.506586
                }
            ],
            "concepts": [
                {
                    "id": "https://openalex.org/C21279758",
                    "wikidata": "https://www.wikidata.org/wiki/Q219409",
                    "display_name": "Venture capital",
                    "level": 2,
                    "score": 0.5884716
                },
                {
                    "id": "https://openalex.org/C146357865",
                    "wikidata": "https://www.wikidata.org/wiki/Q1123245",
                    "display_name": "Stage (stratigraphy)",
                    "level": 2,
                    "score": 0.47407997
                },
                {
                    "id": "https://openalex.org/C162324750",
                    "wikidata": "https://www.wikidata.org/wiki/Q8134",
                    "display_name": "Economics",
                    "level": 0,
                    "score": 0.3705094
                },
                {
                    "id": "https://openalex.org/C144133560",
                    "wikidata": "https://www.wikidata.org/wiki/Q4830453",
                    "display_name": "Business",
                    "level": 0,
                    "score": 0.3551703
                },
                {
                    "id": "https://openalex.org/C10138342",
                    "wikidata": "https://www.wikidata.org/wiki/Q43015",
                    "display_name": "Finance",
                    "level": 1,
                    "score": 0.17133805
                },
                {
                    "id": "https://openalex.org/C127313418",
                    "wikidata": "https://www.wikidata.org/wiki/Q1069",
                    "display_name": "Geology",
                    "level": 0,
                    "score": 0.11989966
                },
                {
                    "id": "https://openalex.org/C151730666",
                    "wikidata": "https://www.wikidata.org/wiki/Q7205",
                    "display_name": "Paleontology",
                    "level": 1,
                    "score": 0.0
                }
            ],
            "mesh": [],
            "locations_count": 1,
            "locations": [
                {
                    "is_oa": false,
                    "landing_page_url": "http://liu.diva-portal.org/smash/record.jsf?pid=diva2:19204",
                    "pdf_url": null,
                    "source": null,
                    "license": null,
                    "license_id": null,
                    "version": null,
                    "is_accepted": false,
                    "is_published": false
                }
            ],
            "best_oa_location": null,
            "sustainable_development_goals": [
                {
                    "score": 0.71,
                    "display_name": "Decent work and economic growth",
                    "id": "https://metadata.un.org/sdg/8"
                }
            ],
            "grants": [],
            "datasets": [],
            "versions": [],
            "referenced_works_count": 2,
            "referenced_works": [
                "https://openalex.org/W2030060017",
                "https://openalex.org/W2114279083"
            ],
            "related_works": [
                "https://openalex.org/W437772578",
                "https://openalex.org/W35966660",
                "https://openalex.org/W340908398",
                "https://openalex.org/W3124112319",
                "https://openalex.org/W3121651344",
                "https://openalex.org/W3042415118",
                "https://openalex.org/W2991021756",
                "https://openalex.org/W2969904317",
                "https://openalex.org/W2766584307",
                "https://openalex.org/W2729599241",
                "https://openalex.org/W2598118406",
                "https://openalex.org/W2592725894",
                "https://openalex.org/W2291094678",
                "https://openalex.org/W2225101278",
                "https://openalex.org/W218379920",
                "https://openalex.org/W2073427251",
                "https://openalex.org/W2062965241",
                "https://openalex.org/W189717603",
                "https://openalex.org/W1603400265",
                "https://openalex.org/W1577063833"
            ],
            "abstract_inverted_index": {
                "Background:": [
                    0
                ],
                "Growth": [
                    1
                ],
                "oriented": [
                    2
                ],
                "entrepreneurial": [
                    3
                ],
                "businesses": [
                    4,
                    19
                ],
                "need": [
                    5
                ],
                "funding": [
                    6
                ],
                "for": [
                    7,
                    17
                ],
                "the": [
                    8,
                    18,
                    21
                ],
                "development": [
                    9
                ],
                "of": [
                    10,
                    25
                ],
                "their": [
                    11
                ],
                "idea,": [
                    12
                ],
                "technology,": [
                    13
                ],
                "product": [
                    14
                ],
                "etc.": [
                    15
                ],
                "However,": [
                    16
                ],
                "in": [
                    20
                ],
                "very": [
                    22
                ],
                "earliest": [
                    23
                ],
                "stages": [
                    24
                ],
                "developmen": [
                    26
                ],
                "...": [
                    27
                ]
            },
            "cited_by_api_url": "https://api.openalex.org/works?filter=cites:W54315794",
            "counts_by_year": [],
            "updated_date": "2024-09-23T23:30:04.695014",
            "created_date": "2016-06-24"
        },
        {
            "id": "https://openalex.org/W2886891038",
            "doi": null,
            "title": "Förmedling av bilar på Internet - en komparativ studie av fyra företag och deras tjänster.",
            "display_name": "Förmedling av bilar på Internet - en komparativ studie av fyra företag och deras tjänster.",
            "publication_year": 2000,
            "publication_date": "2000-01-01",
            "ids": {
                "openalex": "https://openalex.org/W2886891038",
                "mag": "2886891038"
            },
            "language": "en",
            "primary_location": {
                "is_oa": false,
                "landing_page_url": "http://www.diva-portal.org/smash/record.jsf?pid=diva2:1100203",
                "pdf_url": null,
                "source": null,
                "license": null,
                "license_id": null,
                "version": null,
                "is_accepted": false,
                "is_published": false
            },
            "type": "article",
            "type_crossref": "journal-article",
            "indexed_in": [],
            "open_access": {
                "is_oa": false,
                "oa_status": "closed",
                "oa_url": null,
                "any_repository_has_fulltext": false
            },
            "authorships": [
                {
                    "author_position": "first",
                    "author": {
                        "id": "https://openalex.org/A5016768491",
                        "display_name": "Johan Adolfsson",
                        "orcid": null
                    },
                    "institutions": [],
                    "countries": [],
                    "is_corresponding": false,
                    "raw_author_name": "Johan Adolfsson",
                    "raw_affiliation_strings": [],
                    "affiliations": []
                },
                {
                    "author_position": "last",
                    "author": {
                        "id": "https://openalex.org/A5072211155",
                        "display_name": "Jonas Blomqvist",
                        "orcid": null
                    },
                    "institutions": [],
                    "countries": [],
                    "is_corresponding": false,
                    "raw_author_name": "Jonas Blomqvist",
                    "raw_affiliation_strings": [],
                    "affiliations": []
                }
            ],
            "institution_assertions": [],
            "countries_distinct_count": 0,
            "institutions_distinct_count": 0,
            "corresponding_author_ids": [],
            "corresponding_institution_ids": [],
            "apc_list": null,
            "apc_paid": null,
            "fwci": 0.0,
            "has_fulltext": false,
            "cited_by_count": 0,
            "citation_normalized_percentile": {
                "value": 0.0,
                "is_in_top_1_percent": false,
                "is_in_top_10_percent": false
            },
            "cited_by_percentile_year": {
                "min": 0,
                "max": 58
            },
            "biblio": {
                "volume": null,
                "issue": null,
                "first_page": null,
                "last_page": null
            },
            "is_retracted": false,
            "is_paratext": false,
            "primary_topic": {
                "id": "https://openalex.org/T11938",
                "display_name": "Critical Success Factors for ERP Implementation",
                "score": 0.6775,
                "subfield": {
                    "id": "https://openalex.org/subfields/1404",
                    "display_name": "Management Information Systems"
                },
                "field": {
                    "id": "https://openalex.org/fields/14",
                    "display_name": "Business, Management and Accounting"
                },
                "domain": {
                    "id": "https://openalex.org/domains/2",
                    "display_name": "Social Sciences"
                }
            },
            "topics": [
                {
                    "id": "https://openalex.org/T11938",
                    "display_name": "Critical Success Factors for ERP Implementation",
                    "score": 0.6775,
                    "subfield": {
                        "id": "https://openalex.org/subfields/1404",
                        "display_name": "Management Information Systems"
                    },
                    "field": {
                        "id": "https://openalex.org/fields/14",
                        "display_name": "Business, Management and Accounting"
                    },
                    "domain": {
                        "id": "https://openalex.org/domains/2",
                        "display_name": "Social Sciences"
                    }
                },
                {
                    "id": "https://openalex.org/T10734",
                    "display_name": "Information Security Policy Compliance and Awareness",
                    "score": 0.6385,
                    "subfield": {
                        "id": "https://openalex.org/subfields/1710",
                        "display_name": "Information Systems"
                    },
                    "field": {
                        "id": "https://openalex.org/fields/17",
                        "display_name": "Computer Science"
                    },
                    "domain": {
                        "id": "https://openalex.org/domains/3",
                        "display_name": "Physical Sciences"
                    }
                },
                {
                    "id": "https://openalex.org/T11572",
                    "display_name": "Factors Influencing IT-Business Alignment and Governance",
                    "score": 0.6223,
                    "subfield": {
                        "id": "https://openalex.org/subfields/1404",
                        "display_name": "Management Information Systems"
                    },
                    "field": {
                        "id": "https://openalex.org/fields/14",
                        "display_name": "Business, Management and Accounting"
                    },
                    "domain": {
                        "id": "https://openalex.org/domains/2",
                        "display_name": "Social Sciences"
                    }
                }
            ],
            "keywords": [
                {
                    "id": "https://openalex.org/keywords/it-alignment",
                    "display_name": "IT Alignment",
                    "score": 0.486807
                }
            ],
            "concepts": [
                {
                    "id": "https://openalex.org/C110875604",
                    "wikidata": "https://www.wikidata.org/wiki/Q75",
                    "display_name": "The Internet",
                    "level": 2,
                    "score": 0.6940269
                },
                {
                    "id": "https://openalex.org/C178550888",
                    "wikidata": "https://www.wikidata.org/wiki/Q2043282",
                    "display_name": "Business administration",
                    "level": 1,
                    "score": 0.5036265
                },
                {
                    "id": "https://openalex.org/C144133560",
                    "wikidata": "https://www.wikidata.org/wiki/Q4830453",
                    "display_name": "Business",
                    "level": 0,
                    "score": 0.4540757
                },
                {
                    "id": "https://openalex.org/C15708023",
                    "wikidata": "https://www.wikidata.org/wiki/Q80083",
                    "display_name": "Humanities",
                    "level": 1,
                    "score": 0.35955012
                },
                {
                    "id": "https://openalex.org/C142362112",
                    "wikidata": "https://www.wikidata.org/wiki/Q735",
                    "display_name": "Art",
                    "level": 0,
                    "score": 0.13605636
                },
                {
                    "id": "https://openalex.org/C41008148",
                    "wikidata": "https://www.wikidata.org/wiki/Q21198",
                    "display_name": "Computer science",
                    "level": 0,
                    "score": 0.1341362
                },
                {
                    "id": "https://openalex.org/C136764020",
                    "wikidata": "https://www.wikidata.org/wiki/Q466",
                    "display_name": "World Wide Web",
                    "level": 1,
                    "score": 0.07440409
                }
            ],
            "mesh": [],
            "locations_count": 1,
            "locations": [
                {
                    "is_oa": false,
                    "landing_page_url": "http://www.diva-portal.org/smash/record.jsf?pid=diva2:1100203",
                    "pdf_url": null,
                    "source": null,
                    "license": null,
                    "license_id": null,
                    "version": null,
                    "is_accepted": false,
                    "is_published": false
                }
            ],
            "best_oa_location": null,
            "sustainable_development_goals": [
                {
                    "score": 0.41,
                    "display_name": "Decent work and economic growth",
                    "id": "https://metadata.un.org/sdg/8"
                }
            ],
            "grants": [],
            "datasets": [],
            "versions": [],
            "referenced_works_count": 0,
            "referenced_works": [],
            "related_works": [],
            "abstract_inverted_index": {
                "FORMEDLING": [
                    0
                ],
                "AV": [
                    1
                ],
                "BILAR": [
                    2
                ],
                "PA": [
                    3
                ],
                "INTERNET": [
                    4
                ],
                "-": [
                    5,
                    21
                ],
                "en": [
                    6
                ],
                "komparativ": [
                    7
                ],
                "studie": [
                    8
                ],
                "av": [
                    9
                ],
                "fyra": [
                    10
                ],
                "foretag": [
                    11
                ],
                "och": [
                    12
                ],
                "deras": [
                    13
                ],
                "tjanster": [
                    14
                ],
                "Intermediaries": [
                    15
                ],
                "of": [
                    16,
                    25
                ],
                "cars": [
                    17
                ],
                "on": [
                    18
                ],
                "the": [
                    19
                ],
                "Internet": [
                    20
                ],
                "a": [
                    22
                ],
                "comparative": [
                    23
                ],
                "study": [
                    24
                ],
                "four": [
                    26
                ],
                "companies": [
                    27
                ],
                "and": [
                    28
                ],
                "their": [
                    29
                ],
                "services": [
                    30
                ],
                "Uppsats": [
                    33
                ],
                "...": [
                    34
                ]
            },
            "cited_by_api_url": "https://api.openalex.org/works?filter=cites:W2886891038",
            "counts_by_year": [],
            "updated_date": "2024-09-25T23:55:31.077927",
            "created_date": "2018-08-22"
        }
    ],
    "group_by": []
}